mdpfuzz/__init__.py
mdpfuzz/executor.py
mdpfuzz/gmm.py
mdpfuzz/logger.py
mdpfuzz/mdpfuzz.py
mdpfuzz/pool.py
mdpfuzz/utils.py
mdpfuzz-0.0.3.dist-info/licenses/LICENSE
tests/__init__.py
tests/test_gmm.py
tests/test_logger.py
mdpfuzz-0.0.3.dist-info/METADATA
mdpfuzz-0.0.3.dist-info/WHEEL
mdpfuzz-0.0.3.dist-info/top_level.txt
mdpfuzz-0.0.3.dist-info/RECORD
