Metadata-Version: 2.4
Name: mdpfuzz
Version: 0.0.3
Summary: MDPFuzz Replication
Home-page: https://github.com/QuentinMaz/MDPFuzz_Replication/
Author: Mazouni Quentin
Author-email: Mazouni Quentin <quentin@simula.no>
Project-URL: Homepage, https://github.com/QuentinMaz/Replicability_Study/
Project-URL: Issues, https://github.com/QuentinMaz/Replicability_Study/issues
Keywords: mdpfuzz
Classifier: Programming Language :: Python :: 3
Classifier: License :: OSI Approved :: MIT License
Classifier: Operating System :: OS Independent
Requires-Python: >=3.5
License-File: LICENSE
Requires-Dist: numpy
Requires-Dist: pandas
Requires-Dist: tqdm
Requires-Dist: scipy
Requires-Dist: matplotlib
Requires-Dist: pillow
Provides-Extra: test
Requires-Dist: pytest; extra == "test"
Dynamic: author
Dynamic: home-page
Dynamic: license-file
Dynamic: requires-python
